[{"title":"✔现货✔ *多尺寸 压克力球 5个\/组* 可放金莎 喜糖盒 透明球 小礼盒 塑胶球 干燥花球 娃娃球 手工材料 金莎球","price":22},{"title":"圣诞树开花 纸树开花 \/一小包入(定10)  雪树 魔法圣诞树 魔法树 科学实验 纸圣诞树 结晶圣诞树 开花圣诞树","price":5},{"title":"【买10送1】 丝袜 MIT经典透肤丝袜 加大 袜子 无痕 透肤丝袜 不透肤 不易破丝袜 黑丝袜 耐勾丝袜 内刷毛裤袜","price":29},{"title":"YAMAHA YRS-24B 24B 英式 高音 直笛 国小适用 小学三年级 音乐课用具","price":92},{"title":"🔥热销速出🔥保险套湿纸巾套套湿纸巾 宠物湿纸巾 湿巾 恶搞 整人 交换礼物 圣诞节 搞怪 送礼【叶子小铺】","price":3},{"title":"当日完成✨❣️新开幕优惠手绘色块人像画似颜绘无框画｜无脸人像画似颜绘｜情人节 纪念日 生日 周岁 生日礼物｜圣诞交换礼物","price":1},{"title":"【旅行吉他专门店】全新现货《弹指之间》最新 18版 吉他弹唱入门书 潘尚文编著 吉他教材 吉他谱 木吉他 想见你 鱼仔","price":299},{"title":"MIT 无痕不易勾破丝袜 20D 透肤丝袜 丝袜 不易割破 不易勾破 耐勾 台湾发货 裤袜","price":21},{"title":"台湾公司货+开箱影片🔥 零钱盒 找钱神器 自动零钱盒随身零钱盒 台币零钱盒 外送员必备 外送零钱盒","price":199},{"title":"《OPer》普卡两张一元  闪卡一张五元 小卡区 V VMAX TT PTCG 宝可梦 中文版 小朋友 奖品 生日礼物","price":1},{"title":"买十送一 台湾好品质40D高弹力透肤丝袜 显瘦超薄无痕 防勾不易破 女生大尺码丝袜 柜姐 裤袜 OL 隐形丝袜 黑丝袜","price":22},{"title":"LARGE STORE潮流日系休闲工装裤 工作裤 休闲长裤 韩版长裤 男生长裤 9分裤 工装裤 凉感裤 缩口裤(K15)","price":299},{"title":"⭐买10送1⭐四种15D 60D 80D 120D耐勾无痕不易勾破一线档丝袜T档丝袜透肤美肌的弹力丝袜 百搭美腿黑色丝袜","price":13},{"title":"闲鱼代购 淘宝代购  微信  微店 Owhat 阿里巴巴天猫 京东 唯品会 小红书 专业代购 免代购费","price":1},{"title":"【小聪头手作】直播自助下标连结 1元连结 珊瑚玉 散珠 手串 吊坠 直播 下单 随机抓默认有瑕","price":1},{"title":"TOMICA TOMY 多美小汽车  - 胶盒 保护盒 PVC盒 透明盒","price":3},{"title":"虾皮直播商品~破盘商品~999免运、499折运费30","price":1},{"title":"NINE [现货]★强耐韩国透肤丝袜 韩国袜 裤袜 无痕 睡衣 套装 ol 洋装 瘦腿 黑裤 性感 裤 不易破丝袜 耐勾","price":60},{"title":"Instagram手做看板","price":1},{"title":"🍀木木家玩具店🍀 台湾现货 热销15万片 磁力片 散片单片配件 磁力建构片 摩天轮 一代（四代）磁力积木 磁性积木","price":1},{"title":"【圆融文具小妹】含税价 YAMAHA 山叶直笛 Soprano\/Descant 英式 \/ 德式 直笛 YRS-24B","price":78},{"title":"🍄福利舍🍄 ✨现货✨磁力片、磁力片组件包 组合配件 单片磁力片 散片 积木 磁性积木 儿童幼教 补充包 玩具幼儿园、教材","price":1},{"title":"直播自助下单区 《数量下购买商品总金额》","price":1},{"title":"【老羊乐器店】开发票 腕铃 手摇铃 手腕铃 和声花铃鼓 铃鼓  奥福 ORFF  节奏乐器 单卖一个","price":18},{"title":"[超便宜] 一个1元 模型用喷漆夹 夹头 串烧夹 鳄鱼夹 买夹子送竹签 喷漆必备品","price":1},{"title":"【支付宝】充值、代付、代购 相关教学业务谘询服务","price":1},{"title":"筹码币 【全面现货】皇冠筹码 麦穗筹码  麻将筹码 筹码组 筹码 筹码币 代币 加重款14克 适用任何扑克游戏桌游麻将","price":5},{"title":"鬼灭之刃铅笔【QB01】批发现货 24h现货 筒装铅笔 鬼灭之刃 鬼灭 环保考试笔  学生练字铅笔 毕业季 毕业礼物","price":1},{"title":"【M-5XL大尺码】工作裤休闲长裤松紧带休闲裤多口袋宽松束脚裤日系韩版百搭缩口裤长裤透气工作裤哈伦裤加大尺码男生裤","price":195},{"title":"【浩司积木】台湾卖家 现货多款 相容乐高 积木公仔 积木人偶  街景积木 人仔 人偶 公仔 积木公仔 摩托车造型积木","price":10},{"title":"艾比百货》365存钱法 古早味猪公存钱筒 猪造型存钱筒 猪公存钱筒 猪公扑满 猪扑满 存钱筒 猪公 大猪 小猪","price":9},{"title":"&布料共和国& 100D 高密度不透视黑布. 展场用黑布.商场歇业(打烊)用围篱黑布.舞台围黑布.布置.隐密防走光","price":16},{"title":"买家自助下单区（消费多少金额就自行填写多少）","price":1},{"title":"台湾现货天天寄【枕边玩物】一线裆丝袜 性感连裤袜直拼打底袜 裤袜 s101 31-0090、0093、0033、0024","price":14},{"title":"标准盒 宽盒 公仔保护盒 防撞盒 透明盒 现货供应中","price":10},{"title":"🍀台湾现货🍀双面飘移翻滚车 2.4G 充电式 遥控车 翻斗王 双面行驶 翻滚遥控车 四驱翻滚遥控汽车 玩具车 全地形车","price":4},{"title":"泰福晶品选物 直播自助下单区1｜全馆下单1500免运♥卖场规则要注意噢♥","price":1},{"title":"TRITON TC-03 CAPO 移调夹 民谣吉他用 吉他配件 吉他夹 乌克丽丽夹 变调夹 调音夹 汇薪一笑","price":79},{"title":"宇翼国际物流 【集运】大陆寄台湾物流","price":1},{"title":"【老羊乐器店】开发票 三尺寸 吉他弹片 赛璐璐 PICK 匹克 弹片 拨片 0.46mm 0.73mm 1.00mm","price":2},{"title":"韩国代购 韩国代买 NAVER gmarket yes24 twitter 推特 98doci 韩国官网品牌代购","price":1},{"title":"双面玩具钞票  1000元 500元 100元 整人 表演 装饰 聘金 直播 假钞 整人钞票 玩具钞  tw.magic","price":8},{"title":"【499下杀379元】同 UNIQLO版型 透气舒适款 弹性伸缩 侧口袋 工作休闲长裤 加大尺码 4色 #7040","price":369},{"title":"美肌透肤弹力无痕不易勾破丝袜  美腿修饰 透肤丝袜 肤色丝袜 黑色丝袜 耐勾丝袜 袜子 丝袜 丝袜连裤袜【DIFF】","price":15},{"title":"KAZOO 卡祖笛 乌克丽丽\/木吉他伴奏 小叮当的店","price":20},{"title":"水晶直播自助下单区🦒粉晶 紫晶 草莓晶 白水晶 黄水晶 钛晶 海蓝宝 拉长石 天河石 萤石 碧玺 虎眼 黑曜 钛赫兹","price":1},{"title":"直播一元自助下单专用","price":1},{"title":"薄荷巴黎欧美代购二馆9.24","price":1},{"title":"█活动可混搭(不限币别)█玩具\/魔术钞票 新台币 一千元  1000 魔术钞票  假钞票 玩具钞票 1张","price":5},{"title":"直播间连结500包运","price":1},{"title":"【现货】 皇冠筹码 皇冠筹码 陶土含铁筹码 14g加重筹码 麻将 德州扑克 百家乐 21点 拉斯维加斯","price":3},{"title":"水晶直播自助下单区🔮粉晶 紫晶 草莓晶 白水晶 黄水晶 钛晶 海蓝宝 拉长石 天河石 萤石 碧玺 虎眼 紫锂辉 黑曜","price":1},{"title":"🔥台湾现货免运🔥防勾丝袜 台湾制造 台湾丝袜 MIT 皮肤色 黑丝袜 肤色丝袜 防晒丝袜 显瘦丝袜 遮瑕丝袜","price":29},{"title":"直播自助下单专区：数量=金额","price":1},{"title":"泰福晶品选物 直播自助下单区3｜全馆下单1500免运♥卖场规则要注意噢♥","price":1},{"title":"直播自助下单区✓✓✓✓","price":1},{"title":"直播自助下标连结 1元连结 水晶手串 直播下单","price":1},{"title":"【叶精灵小栈】全套神兽配到好 冠之雪原 宝可梦剑盾 色违 6v 配布 全图鉴 幻兽 客制化 订制 神兽 配布 配信","price":1},{"title":"一件免运【台湾现货】【NO1销售破万件】G1 评价破万 加厚款 轻薄款 弹性伸缩侧口袋工作裤  IFOA","price":349},{"title":"沙龙款 鳄鱼夹 恐龙夹 怪兽夹 美发夹 止滑 防滑 发夹 发饰 【DT STORE】【0322122】","price":9}]